{"name":"build-javascript","namedChunkGroups":{"polyfill":{"name":"polyfill","assets":[{"name":"webpack-runtime-a27257dd272e69b0b6e8.js","size":5224},{"name":"polyfill-aaae15c64eb65067c66d.js","size":85860}],"filteredAssets":0,"assetsSize":91084,"filteredAuxiliaryAssets":2,"auxiliaryAssetsSize":228410},"app":{"name":"app","assets":[{"name":"webpack-runtime-a27257dd272e69b0b6e8.js","size":5224},{"name":"framework-b52b0d62d6513fe416a0.js","size":130501},{"name":"app-8a6bf398f4065fcf481e.js","size":55672}],"filteredAssets":0,"assetsSize":191397,"filteredAuxiliaryAssets":3,"auxiliaryAssetsSize":565900},"component---src-pages-404-js":{"name":"component---src-pages-404-js","assets":[{"name":"component---src-pages-404-js-3b116a8fa1e7fb5797c0.js","size":825}],"filteredAssets":0,"assetsSize":825,"filteredAuxiliaryAssets":1,"auxiliaryAssetsSize":1892},"component---src-pages-index-js":{"name":"component---src-pages-index-js","assets":[{"name":"framework-b52b0d62d6513fe416a0.js","size":130501},{"name":"styles.44f09b110f11eaca70c0.css","size":8053},{"name":"1bfc9850-7f5088eb5e9faf7f54f9.js","size":857},{"name":"cb1608f2-f397d0720d411e3ba7e3.js","size":765},{"name":"a9a7754c-6ff3902d9c1eab1fe47b.js","size":2840},{"name":"f5ce3888-6fde9ae87187de98b513.js","size":485088},{"name":"2c796e83-8fa83b621380b5ca8224.js","size":1007552},{"name":"61c5db6db8ab0e4113ff5d8f80534dc7bf5ce498-0bf616b065327a770b53.js","size":340740},{"name":"component---src-pages-index-js-be6f90059805db84b353.js","size":31207}],"filteredAssets":0,"assetsSize":2007603,"filteredAuxiliaryAssets":28,"auxiliaryAssetsSize":27215568},"component---src-pages-report-js":{"name":"component---src-pages-report-js","assets":[{"name":"framework-b52b0d62d6513fe416a0.js","size":130501},{"name":"styles.44f09b110f11eaca70c0.css","size":8053},{"name":"1bfc9850-7f5088eb5e9faf7f54f9.js","size":857},{"name":"cb1608f2-f397d0720d411e3ba7e3.js","size":765},{"name":"a9a7754c-6ff3902d9c1eab1fe47b.js","size":2840},{"name":"61c5db6db8ab0e4113ff5d8f80534dc7bf5ce498-0bf616b065327a770b53.js","size":340740}],"filteredAssets":0,"assetsSize":483756,"filteredAuxiliaryAssets":24,"auxiliaryAssetsSize":23472863}},"assetsByChunkName":{"polyfill":["webpack-runtime-a27257dd272e69b0b6e8.js","polyfill-aaae15c64eb65067c66d.js"],"app":["webpack-runtime-a27257dd272e69b0b6e8.js","framework-b52b0d62d6513fe416a0.js","app-8a6bf398f4065fcf481e.js"],"component---src-pages-404-js":["component---src-pages-404-js-3b116a8fa1e7fb5797c0.js"],"component---src-pages-index-js":["framework-b52b0d62d6513fe416a0.js","styles.44f09b110f11eaca70c0.css","1bfc9850-7f5088eb5e9faf7f54f9.js","cb1608f2-f397d0720d411e3ba7e3.js","a9a7754c-6ff3902d9c1eab1fe47b.js","f5ce3888-6fde9ae87187de98b513.js","2c796e83-8fa83b621380b5ca8224.js","61c5db6db8ab0e4113ff5d8f80534dc7bf5ce498-0bf616b065327a770b53.js","component---src-pages-index-js-be6f90059805db84b353.js"],"component---src-pages-report-js":["framework-b52b0d62d6513fe416a0.js","styles.44f09b110f11eaca70c0.css","1bfc9850-7f5088eb5e9faf7f54f9.js","cb1608f2-f397d0720d411e3ba7e3.js","a9a7754c-6ff3902d9c1eab1fe47b.js","61c5db6db8ab0e4113ff5d8f80534dc7bf5ce498-0bf616b065327a770b53.js"]},"childAssetsByChunkName":{}}